icarus_v2/__init__.py
icarus_v2/__main__.py
icarus_v2/backend/__init__.py
icarus_v2/backend/buffer_loader.py
icarus_v2/backend/configuration_manager.py
icarus_v2/backend/csv_exporter.py
icarus_v2/backend/data_handler.py
icarus_v2/backend/dataq_interface.py
icarus_v2/backend/depressurize_handler.py
icarus_v2/backend/event.py
icarus_v2/backend/event_handler.py
icarus_v2/backend/log_handler.py
icarus_v2/backend/log_reader.py
icarus_v2/backend/logger.py
icarus_v2/backend/period_handler.py
icarus_v2/backend/pressure_handler.py
icarus_v2/backend/pressurize_handler.py
icarus_v2/backend/pulse_generator.py
icarus_v2/backend/pump_handler.py
icarus_v2/backend/ring_buffer.py
icarus_v2/backend/sample_sensor_detector.py
icarus_v2/backend/sentry.py
icarus_v2/backend/sentry_error.py
icarus_v2/backend/sentry_warning.py
icarus_v2/gui/__init__.py
icarus_v2/gui/counter_display.py
icarus_v2/gui/device_control_panel.py
icarus_v2/gui/error_dialog.py
icarus_v2/gui/event_plot.py
icarus_v2/gui/history_plot.py
icarus_v2/gui/image_button.py
icarus_v2/gui/log_control_panel.py
icarus_v2/gui/main_window.py
icarus_v2/gui/pressure_display.py
icarus_v2/gui/scrollable_menu.py
icarus_v2/gui/settings_dialog.py
icarus_v2/gui/styled_plot_widget.py
icarus_v2/gui/tool_bar.py
icarus_v2/qdarktheme/LICENSE.txt
icarus_v2/qdarktheme/README.md
icarus_v2/qdarktheme/__init__.py
icarus_v2/qdarktheme/color.py
icarus_v2/qdarktheme/hsla.py
icarus_v2/qdarktheme/load_style.py
icarus_v2/qdarktheme/rgba.py
icarus_v2/qdarktheme/styles.qss
icarus_v2/qdarktheme/svg.py
icarus_v2/resources/__init__.py
icarus_v2/resources/app-screenshot.png
icarus_v2/resources/default_settings.json
icarus_v2/resources/export_icon.svg
icarus_v2/resources/setup/70-dataq-di-4108.rules
icarus_v2/resources/setup/install_udev_rules.sh
icarus_v2/resources/shutdown.svg
icarus_v2/resources/wing.png
icarus_v2/utils/__init__.py
icarus_v2/utils/raw_log_reader.py
icarus_v2/utils/udev_setup.py
icarus_v2-0.3.8.dist-info/LICENSE.txt
icarus_v2-0.3.8.dist-info/METADATA
icarus_v2-0.3.8.dist-info/WHEEL
icarus_v2-0.3.8.dist-info/entry_points.txt
icarus_v2-0.3.8.dist-info/RECORD
