Metadata-Version: 2.1
Name: icarus_v2
Version: 0.3.8
Summary: Monitoring software for the Icarus Pressure Jump apparatus
Home-page: https://github.com/SeanIFitch/icarus_v2
Author: Sean Fitch
Author-email: fitchs2@rpi.edu
Requires-Python: >=3.10,<3.13
Classifier: License :: OSI Approved :: MIT License
Classifier: Operating System :: Unix
Classifier: Programming Language :: Python :: 3
Classifier: Programming Language :: Python :: 3.10
Classifier: Programming Language :: Python :: 3.11
Classifier: Programming Language :: Python :: 3.12
Classifier: Topic :: Scientific/Engineering
Requires-Dist: PySide6 (>=6.7,<6.8)
Requires-Dist: PySide6_Addons (>=6.7,<6.8)
Requires-Dist: PySide6_Essentials (>=6.7,<6.8)
Requires-Dist: numpy (>=2.1,<3.0)
Requires-Dist: pyqtgraph (>=0.13,<0.14)
Requires-Dist: pyusb (>=1.2,<2.0)
Requires-Dist: shiboken6 (>=6.7,<6.8)
Project-URL: Bug Tracker, https://github.com/SeanIFitch/icarus_v2/issues
Project-URL: Repository, https://github.com/SeanIFitch/icarus_v2
